{
  "${ModID}:SummonBulldog": {
    "NAME": "Summon Bulldog",
    "DESCRIPTION": "Channel a !M! damage ${ModID}:Bulldog."
  },
  "${ModID}:SummonVegetables": {
    "NAME": "Summon Vegetables",
    "DESCRIPTION": "Deal !D! damage for each Skill played this turn.",
    "EXTENDED_DESCRIPTION": [
      " NL (",
      " Skill played.)",
      " Skills played.)"
      ]
  },
  "${ModID}:SummonTrees": {
    "NAME": "Summon Trees",
    "DESCRIPTION": "Gain !B! Block. NL Take !M! less damage from Attacks this turn."
  },
  "${ModID}:SummonElephant": {
    "NAME": "Summon Elephant",
    "DESCRIPTION": "Deal !D! damage to ALL enemies. NL Take !M! damage."
  },
  "${ModID}:SummonBrambles": {
    "NAME": "Summon Brambles",
    "DESCRIPTION": "Gain !B! Block. NL Gain !M! Thorns."
  },
  "${ModID}:SummonPython": {
    "NAME": "Summon Python",
    "DESCRIPTION": "Apply !M! ${ModID}:Constricted. NL Exhaust."
  },
  "${ModID}:SummonBees": {
    "NAME": "Summon Bees",
    "DESCRIPTION": "Channel !M! ${ModID}:Swarms\u00a0of\u00a0Bees. NL Exhaust."
  },
  "${ModID}:Control": {
    "NAME": "Control",
    "DESCRIPTION": "Gain !M! Orb slots and !M! Focus."
  },
  "${ModID}:DemonicRitual": {
    "NAME": "Demonic Ritual",
    "DESCRIPTION": "Exhaust your hand. NL Gain Strength equal to its total cost.",
    "UPGRADE_DESCRIPTION": "Exhaust your hand. NL Gain Strength equal to its total cost + !M!."
  },
  "${ModID}:SummonPandas": {
    "NAME": "Summon Pandas",
    "DESCRIPTION": "At the start of your turn, Channel a !M! damage ${ModID}:Panda."
  }
}