{
  "${ModID}:ShedWeight": {
    "NAME": "Shed Weight",
    "DESCRIPTION": "Gain !B! Block. NL Discard a card. NL If that card was *Unplayable, draw a card."
  },
  "${ModID}:RayOfFrost": {
    "NAME": "Ray Of Frost",
    "DESCRIPTION": "Deal !D! damage. NL ${ModID}:Amplify [E] : Channel !M! Frost."
  },
  "${ModID}:Swipe": {
    "NAME": "Swipe",
    "DESCRIPTION": "Deal !D! damage for each point of Energy missing.",
    "EXTENDED_DESCRIPTION": [" NL (Hits !M! times.)"]
  },
  "${ModID}:Ambition": {
    "NAME": "Ambition",
    "DESCRIPTION": "Put a random Power from your draw pile into your hand and copy it. NL Exhaust.",
    "UPGRADE_DESCRIPTION": "Innate. NL Put a random Power from your draw pile into your hand and copy it. NL Exhaust."
  },
  "${ModID}:Diehard": {
    "NAME": "Diehard",
    "DESCRIPTION": "Gain !M! Artifact. NL Next turn, gain 1 Weak and Frail."
  },
  "${ModID}:EldritchBlast": {
    "NAME": "Eldritch Blast",
    "DESCRIPTION": "Deal !D! damage. NL Whenever you play a Power, return this from your discard pile to your hand."
  },
  "${ModID}:DeathWish": {
    "NAME": "Death Wish",
    "DESCRIPTION": "If your HP is above 50%, lose !M! HP. NL Gain !M! Strength and *Vigor."
  },
  "${ModID}:KillerInstinct": {
    "NAME": "Killer Instinct",
    "DESCRIPTION": "Gain 2 Strength and 1 Dexterity. NL Startup: Shuffle a copy of this card into your draw pile.",
    "UPGRADE_DESCRIPTION": "Gain 2 Strength and 1 Dexterity. NL Startup: Shuffle !M! copies of this card into your draw pile."
  },
  "${ModID}:Bulwark": {
    "NAME": "Bulwark",
    "DESCRIPTION": "Innate. NL Gain Temporary HP equal to your draw pile size. NL Exhaust.",
    "EXTENDED_DESCRIPTION": [" NL (Gain !M! Temporary HP.)"]
  },
  "${ModID}:Masterstroke": {
    "NAME": "Masterstroke",
    "DESCRIPTION": "Gain !B! Block. NL Deal !D! damage. NL Strength and Dexterity affect this card !M! times."
  }
}